{
  "FLAME": {
    "NAME": "Flame",
    "EFFECTS": { 
      "FIRE_DAMAGE_TARGET": 1 
      },
    "VALUE_MULTIPLIER": 2
  },
  "SHARD": {
    "NAME": "Shard",
    "EFFECTS": { 
      "FROST_DAMAGE_TARGET": 1 
      },
    "VALUE_MULTIPLIER": 2
  },
  "SPARK": {
    "NAME": "Spark",
    "EFFECTS": { 
      "SHOCK_DAMAGE_TARGET": 1 
      },
    "VALUE_MULTIPLIER": 2
  },
  "VIPER": {
    "NAME": "Viper",
    "EFFECTS": { 
      "POISON_DAMAGE_TARGET": 1 
      },
    "VALUE_MULTIPLIER": 2
  },
  "FIRE": {
    "NAME": "Fire",
    "EFFECTS": { 
      "FIRE_DAMAGE_TARGET": 3 
      },
    "VALUE_MULTIPLIER": 2.8
  },
  "FROST": {
    "NAME": "Frost",
    "EFFECTS": { 
      "FROST_DAMAGE_TARGET": 3
      },
    "VALUE_MULTIPLIER": 2.8
  },
  "STORM": {
    "NAME": "Storm",
    "EFFECTS": { 
      "SHOCK_DAMAGE_TARGET": 3
      },
    "VALUE_MULTIPLIER": 2.8
  },
  "POISON": {
    "NAME": "Poison",
    "EFFECTS": { 
      "POISON_DAMAGE_TARGET": 3 
      },
    "VALUE_MULTIPLIER": 2.8
  },
  "CHASTENING": {
    "NAME": "Chastening",
    "EFFECTS": {
      "REMOVE_EVASION_TARGET": 3
      },
    "VALUE_MULTIPLIER": 1.5
  },
  "JUDGMENT": {
    "NAME": "Judgment",
    "EFFECTS": { 
      "APPLY_DAMAGE_ENDURANCE_TARGET": 3
      },
    "VALUE_MULTIPLIER": 2
  },
  "RECKONING": {
    "NAME": "Reckoning",
    "EFFECTS": { 
      "APPLY_DAMAGE_SPEED_TARGET": 2
      },
    "VALUE_MULTIPLIER": 3
  },
  "SHAMING": {
    "NAME": "Shaming",
    "EFFECTS": { 
      "APPLY_DAMAGE_INTELLIGENCE_TARGET": 3
      },
    "VALUE_MULTIPLIER": 2.5
  },
  "WAR": {
    "NAME": "War",
    "EFFECTS": { 
    "FIRE_DAMAGE_TARGET": 1,
    "FROST_DAMAGE_TARGET": 1,
    "SHOCK_DAMAGE_TARGET": 1
    },
    "VALUE_MULTIPLIER": 3
  },
  "PEACE": {
    "NAME": "Peace",
    "EFFECTS": { 
      "APPLY_PARALYZE_TARGET": 1 
      },
    "VALUE_MULTIPLIER": 4
  }
}
